{"skeleton":{"hash":"UrEMTR2UD9ehU9OigzNJKl2E2DA","spine":"3.8.75","x":-32.42,"y":-4.45,"width":59,"height":65,"images":"C:/Users/KienNT/Downloads/images/","audio":""},"bones":[{"name":"root"},{"name":"bone","parent":"root","x":-0.14,"y":-29.68},{"name":"bullet_tesla_mini_6","parent":"bone","x":1.98,"y":55.3}],"slots":[{"name":"bullet_tesla_mini_0","bone":"bullet_tesla_mini_6","attachment":"bullet_tesla_mini_0"},{"name":"bullet_tesla_mini_1","bone":"bullet_tesla_mini_6"},{"name":"bullet_tesla_mini_2","bone":"bullet_tesla_mini_6"},{"name":"bullet_tesla_mini_3","bone":"bullet_tesla_mini_6"},{"name":"bullet_tesla_mini_4","bone":"bullet_tesla_mini_6"},{"name":"bullet_tesla_mini_5","bone":"bullet_tesla_mini_6"},{"name":"bullet_tesla_mini_6","bone":"bullet_tesla_mini_6"},{"name":"bullet_tesla_mini_7","bone":"bullet_tesla_mini_6"},{"name":"bullet_tesla_mini_8","bone":"bullet_tesla_mini_6"}],"skins":[{"name":"default","attachments":{"bullet_tesla_mini_0":{"bullet_tesla_mini_0":{"x":-4.77,"y":2.43,"width":59,"height":65}},"bullet_tesla_mini_1":{"bullet_tesla_mini_1":{"x":-6,"y":1.14,"width":62,"height":62}},"bullet_tesla_mini_2":{"bullet_tesla_mini_2":{"x":-2.71,"y":2.22,"width":72,"height":59}},"bullet_tesla_mini_3":{"bullet_tesla_mini_3":{"x":-2.98,"y":0.74,"width":72,"height":56}},"bullet_tesla_mini_4":{"bullet_tesla_mini_4":{"x":-0.63,"y":1.2,"width":68,"height":60}},"bullet_tesla_mini_5":{"bullet_tesla_mini_5":{"x":0.32,"y":1.6,"width":71,"height":63}},"bullet_tesla_mini_6":{"bullet_tesla_mini_6":{"x":-0.61,"y":0.16,"width":71,"height":68}},"bullet_tesla_mini_7":{"bullet_tesla_mini_7":{"x":-3.34,"y":1.7,"width":62,"height":57}},"bullet_tesla_mini_8":{"bullet_tesla_mini_8":{"x":-3.11,"y":0.47,"width":59,"height":62}}}}],"animations":{"animation":{"slots":{"bullet_tesla_mini_8":{"attachment":[{"time":0.5333,"name":"bullet_tesla_mini_8"}]},"bullet_tesla_mini_0":{"attachment":[{"time":0.0667,"name":null}]},"bullet_tesla_mini_1":{"attachment":[{"time":0.0667,"name":"bullet_tesla_mini_1"},{"time":0.1333,"name":null}]},"bullet_tesla_mini_4":{"attachment":[{"time":0.2667,"name":"bullet_tesla_mini_4"},{"time":0.3333,"name":null}]},"bullet_tesla_mini_7":{"attachment":[{"time":0.4667,"name":"bullet_tesla_mini_7"},{"time":0.5333,"name":null}]},"bullet_tesla_mini_3":{"attachment":[{"time":0.2,"name":"bullet_tesla_mini_3"},{"time":0.2667,"name":null}]},"bullet_tesla_mini_2":{"attachment":[{"time":0.1333,"name":"bullet_tesla_mini_2"},{"time":0.2,"name":null}]},"bullet_tesla_mini_6":{"attachment":[{"time":0.4,"name":"bullet_tesla_mini_6"},{"time":0.4667,"name":null}]},"bullet_tesla_mini_5":{"attachment":[{"time":0.3333,"name":"bullet_tesla_mini_5"},{"time":0.4,"name":null}]}}}}}